autoviml/Auto_NLP.py
autoviml/Auto_ViML.py
autoviml/QuickML_Ensembling.py
autoviml/QuickML_Stacking.py
autoviml/Transform_KM_Features.py
autoviml/__init__.py
autoviml/__version__.py
autoviml/classify_method.py
autoviml/custom_scores.py
autoviml/custom_scores_HO.py
autoviml/feature_engineering.py
autoviml/sulov_method.py
autoviml-0.2.2.dist-info/LICENSE
autoviml-0.2.2.dist-info/METADATA
autoviml-0.2.2.dist-info/WHEEL
autoviml-0.2.2.dist-info/top_level.txt
autoviml-0.2.2.dist-info/RECORD
