Metadata-Version: 2.2
Name: autoviml
Version: 0.2.2
Summary: Automatically Build Variant Interpretable ML models fast - now with CatBoost!
Home-page: https://github.com/AutoViML/Auto_ViML
Author: Ram Seshadri
License: Apache License 2.0
Classifier: Programming Language :: Python :: 3
Classifier: Operating System :: OS Independent
License-File: LICENSE
Requires-Dist: numpy<2
Requires-Dist: pandas>=2.0
Requires-Dist: scipy==1.11.4
Requires-Dist: xlrd
Requires-Dist: matplotlib>3.7.4
Requires-Dist: beautifulsoup4
Requires-Dist: emoji
Requires-Dist: ipython
Requires-Dist: jupyter
Requires-Dist: seaborn
Requires-Dist: catboost>=1.2.7
Requires-Dist: textblob
Requires-Dist: nltk
Requires-Dist: regex
Requires-Dist: xgboost<=1.7.6,>=0.82
Requires-Dist: vaderSentiment
Requires-Dist: imbalanced-learn>=0.10.1
Requires-Dist: shap>=0.36.0
Requires-Dist: scikit-learn<=1.5.2,>=0.24
Requires-Dist: lightgbm>=3.0.0
Requires-Dist: networkx>=3.1
Requires-Dist: pandas-dq>=1.29
Dynamic: author
Dynamic: classifier
Dynamic: description
Dynamic: description-content-type
Dynamic: home-page
Dynamic: license
Dynamic: requires-dist
Dynamic: summary
